Cellcano/__init__.py
Cellcano/main.py
Cellcano/predict.py
Cellcano/preprocess.py
Cellcano/train.py
Cellcano-0.0.1.dist-info/LICENSE
Cellcano-0.0.1.dist-info/METADATA
Cellcano-0.0.1.dist-info/WHEEL
Cellcano-0.0.1.dist-info/entry_points.txt
Cellcano-0.0.1.dist-info/top_level.txt
Cellcano-0.0.1.dist-info/RECORD
