Metadata-Version: 2.1
Name: Cellcano
Version: 0.0.1
Summary: Cellcano is for supervised cell type identification (celltyping) in single-cell genomics.
Home-page: https://github.com/marvinquiet/Cellcano
Author: Wenjing Ma
Author-email: wenjing.ma@emory.edu
License: MIT
Project-URL: Documentation, https://marvinquiet.github.io/Cellcano/
Project-URL: Bug Tracker, https://github.com/marvinquiet/Cellcano/issues
Platform: UNKNOWN
Requires-Python: >=3.8
License-File: LICENSE
